mycalc/calculator.py
dayy9984-0.0.1.dist-info/METADATA
dayy9984-0.0.1.dist-info/WHEEL
dayy9984-0.0.1.dist-info/top_level.txt
dayy9984-0.0.1.dist-info/RECORD
