Metadata-Version: 2.1
Name: dayy9984
Version: 0.0.1
Summary: oss-dev my calculator 0001
Home-page: https://github.com/Dayy9984/OSS_Donga
Download-URL: https://github.com/Dayy9984/OSS_Donga
Author: dayy9984
License: UNKNOWN
Platform: UNKNOWN
Classifier: Programming Language :: Python :: 3
